gmail_yaml_filters/__init__.py
gmail_yaml_filters/main.py
gmail_yaml_filters/upload.py
gmail_yaml_filters-0.4.dist-info/DESCRIPTION.rst
gmail_yaml_filters-0.4.dist-info/METADATA
gmail_yaml_filters-0.4.dist-info/RECORD
gmail_yaml_filters-0.4.dist-info/WHEEL
gmail_yaml_filters-0.4.dist-info/entry_points.txt
gmail_yaml_filters-0.4.dist-info/metadata.json
gmail_yaml_filters-0.4.dist-info/top_level.txt
